contrast_agent_lib/__init__.py
contrast_agent_lib/constants/__init__.py
contrast_agent_lib/libs/libcontrast_c_musl_aarch64.so
contrast_agent_lib.libs/ld-musl-aarch64-c5179263.so.1
contrast_agent_lib-0.12.0.dist-info/METADATA
contrast_agent_lib-0.12.0.dist-info/WHEEL
contrast_agent_lib-0.12.0.dist-info/top_level.txt
contrast_agent_lib-0.12.0.dist-info/RECORD
contrast_agent_lib-0.12.0.dist-info/licenses/LICENSE.txt
