Metadata-Version: 2.4
Name: contrast-agent-lib
Version: 0.12.0
Summary: Python interface to the contrast agent lib
Author-email: "Contrast Security, Inc." <python@contrastsecurity.com>
License: CONTRAST SECURITY (see LICENSE.txt)
Project-URL: homepage, https://www.contrastsecurity.com
Project-URL: support, https://support.contrastsecurity.com
Classifier: Development Status :: 2 - Pre-Alpha
Classifier: Intended Audience :: Developers
Classifier: Programming Language :: Python :: 3
Requires-Python: >=3.9
License-File: LICENSE.txt
Dynamic: license-file
